README.rst
setup.py
megaparsy/__about__.py
megaparsy/__init__.py
megaparsy/utils.py
megaparsy.egg-info/PKG-INFO
megaparsy.egg-info/SOURCES.txt
megaparsy.egg-info/dependency_links.txt
megaparsy.egg-info/requires.txt
megaparsy.egg-info/top_level.txt
megaparsy/char/__init__.py
megaparsy/char/lexer.py
megaparsy/control/__init__.py
megaparsy/control/applicative/__init__.py
megaparsy/control/applicative/combinators.py