Metadata-Version: 1.1
Name: megaparsy
Version: 0.1.4
Summary: Library porting many of the combinators from Haskell's Megaparsec for use with Python's Parsy.
Home-page: https://github.com/anentropic/megaparsy
Author: Anentropic
Author-email: ego@anentropic.com
License: MIT
Platform: UNKNOWN
Classifier: Intended Audience :: Developers
Classifier: License :: OSI Approved :: MIT License
Classifier: Operating System :: OS Independent
Classifier: Programming Language :: Python
Classifier: Programming Language :: Python :: 3
Classifier: Topic :: Text Processing
